{
  "seriesId": "robin-hood-schlitzohr-von-sherwood",
  "title": "Robin Hood - Schlitzohr von Sherwood",
  "language": "de",
  "author": "",
  "narrator": "",
  "genres": [
    "Hörspiele"
  ],
  "albums": [
    {
      "id": "1807077980",
      "title": "Episode 36: Samsons Rückkehr (Das Original-Hörspiel zur TV-Serie)",
      "episodeNumber": null,
      "releaseDate": null,
      "coverURL": "https://is1-ssl.mzstatic.com/image/thumb/Music221/v4/fa/bc/09/fabc090e-83a1-c446-a68a-52bd35f57264/cover.jpg/100x100bb.jpg",
      "description": "Dieses Album ist das Original-Hörspiel zur TV-Serie 'Robin Hood - Schlitzohr von Sherwood'. Es umfasst 18 Tracks im Genre Hörspiel.",
      "totalDuration": 0,
      "platforms": {
        "appleMusic": "1807077980"
      },
      "chapters": []
    },
    {
      "id": "1807050831",
      "title": "Episode 37: Der Rächer aus dem Pferdestall (Das Original-Hörspiel zur TV-Serie)",
      "episodeNumber": null,
      "releaseDate": null,
      "coverURL": "https://is1-ssl.mzstatic.com/image/thumb/Music221/v4/c5/9d/dc/c59ddcfd-a8f0-09f3-e695-f75043450f51/cover.jpg/100x100bb.jpg",
      "description": "Dieses Album enthält das Original-Hörspiel zur TV-Serie 'Robin Hood - Schlitzohr von Sherwood'. Es handelt sich um ein Hörspiel.",
      "totalDuration": 0,
      "platforms": {
        "appleMusic": "1807050831"
      },
      "chapters": []
    },
    {
      "id": "1808678734",
      "title": "Episode 38: Die fürstlichen Spiele (Das Original-Hörspiel zur TV-Serie)",
      "episodeNumber": null,
      "releaseDate": null,
      "coverURL": "https://is1-ssl.mzstatic.com/image/thumb/Music221/v4/16/2d/11/162d11d8-f7f8-076e-d9ee-1b91e8d6e7e2/cover.jpg/100x100bb.jpg",
      "description": "Ein Album, das als Original-Hörspiel zur TV-Serie 'Die Fürstlichen Spiele' erscheint, deutet eindeutig auf ein Hörspiel hin, da es als 'Episode 38: Die Fürstlichen Spiele' vermarktet wird.",
      "totalDuration": 0,
      "platforms": {
        "appleMusic": "1808678734"
      },
      "chapters": []
    },
    {
      "id": "1808681634",
      "title": "Episode 39: Eine einfache Dienerin (Das Original-Hörspiel zur TV-Serie)",
      "episodeNumber": null,
      "releaseDate": null,
      "coverURL": "https://is1-ssl.mzstatic.com/image/thumb/Music221/v4/c6/a3/23/c6a3231f-7dff-2344-c8e4-8852be860f86/cover.jpg/100x100bb.jpg",
      "description": "Ein Album, das ein Hörspiel mit dem Titel 'Episode 39: Eine einfache Dienerin' beinhaltet, das als Original-Hörspiel zur TV-Serie 'Robin Hood - Schlitzohr von Sherwood' veröffentlicht wurde. Es enthält 18 Tracks im Genre Hörspiele.",
      "totalDuration": 0,
      "platforms": {
        "appleMusic": "1808681634"
      },
      "chapters": []
    },
    {
      "id": "1567214876",
      "title": "Folge 10: Der Trottel (Das Original-Hörspiel zur TV-Serie)",
      "episodeNumber": null,
      "releaseDate": null,
      "coverURL": "https://is1-ssl.mzstatic.com/image/thumb/Music115/v4/c6/28/5d/c6285d73-b589-54d7-cd91-25b9ea56bf91/cover.jpg/100x100bb.jpg",
      "description": "Ein Album, das als Hörspiel zur TV-Serie 'Robin Hood - Schlitzohr von Sherwood' erscheint, deutet eindeutig auf eine Hörspielproduktion hin.",
      "totalDuration": 0,
      "platforms": {
        "appleMusic": "1567214876"
      },
      "chapters": []
    },
    {
      "id": "1276246535",
      "title": "Folge 11: Räuberspiele (Das Original-Hörspiel zur TV-Serie)",
      "episodeNumber": null,
      "releaseDate": null,
      "coverURL": "https://is1-ssl.mzstatic.com/image/thumb/Music115/v4/e0/66/b3/e066b314-b3df-e64f-3b85-3da2082b05d6/cover.jpg/100x100bb.jpg",
      "description": "Dieses Album ist das Original-Hörspiel zur TV-Serie \"Robin Hood - Schlitzohr von Sherwood\". Es umfasst 25 Tracks im Genre \"Hörspiele\".",
      "totalDuration": 0,
      "platforms": {
        "appleMusic": "1276246535"
      },
      "chapters": []
    },
    {
      "id": "1341643945",
      "title": "Folge 12: Der geheime Garten (Das Original-Hörspiel zur TV-Serie)",
      "episodeNumber": null,
      "releaseDate": null,
      "coverURL": "https://is1-ssl.mzstatic.com/image/thumb/Music125/v4/53/45/29/5345297a-d120-4544-dfd2-2dc30077a6f9/cover.jpg/100x100bb.jpg",
      "description": "Dieses Album ist das Original-Hörspiel zur TV-Serie 'Robin Hood - Schlitzohr von Sherwood'. Es enthält insgesamt 26 Tracks und gehört zur Kategorie Hörspiele.",
      "totalDuration": 0,
      "platforms": {
        "appleMusic": "1341643945"
      },
      "chapters": []
    },
    {
      "id": "1539218771",
      "title": "Folge 13: Es war einmal in Nottingham (Das Original Hörspiel zur TV-Serie)",
      "episodeNumber": null,
      "releaseDate": null,
      "coverURL": "https://is1-ssl.mzstatic.com/image/thumb/Music125/v4/b2/e8/9c/b2e89ca3-654b-afe1-daba-a6075454ee22/cover.jpg/100x100bb.jpg",
      "description": "Dieses Album enthält das Original-Hörspiel zur TV-Serie \"Robin Hood - Schlitzohr von Sherwood\" mit 16 Episoden.",
      "totalDuration": 0,
      "platforms": {
        "appleMusic": "1539218771"
      },
      "chapters": []
    },
    {
      "id": "1477954937",
      "title": "Folge 14: Robin und der König (Das Original-Hörspiel zur TV-Serie)",
      "episodeNumber": null,
      "releaseDate": null,
      "coverURL": "https://is1-ssl.mzstatic.com/image/thumb/Music124/v4/bc/e3/2a/bce32a7b-1a64-4ea1-218e-1086662b8be8/cover.jpg/100x100bb.jpg",
      "description": "Dieses Album ist das Original-Hörspiel zur TV-Serie \"Robin Hood - Schlitzohr von Sherwood\", das sich auf ein Abenteuer in Fantasy-Welt konzentriert.",
      "totalDuration": 0,
      "platforms": {
        "appleMusic": "1477954937"
      },
      "chapters": []
    },
    {
      "id": "1501185684",
      "title": "Folge 15: Ein gefährlicher Geburtstag (Das Original-Hörspiel zur TV-Serie)",
      "episodeNumber": null,
      "releaseDate": null,
      "coverURL": "https://is1-ssl.mzstatic.com/image/thumb/Music114/v4/9d/ae/b3/9daeb3a6-6788-59c2-12af-20a8586cc54c/cover.jpg/100x100bb.jpg",
      "description": "Ein Hörspiel zur TV-Serie, das auf einem Album veröffentlicht ist.",
      "totalDuration": 0,
      "platforms": {
        "appleMusic": "1501185684"
      },
      "chapters": []
    },
    {
      "id": "1518807912",
      "title": "Folge 16: Der Mann mit der Maske (Das Original-Hörspiel zur TV-Serie)",
      "episodeNumber": null,
      "releaseDate": null,
      "coverURL": "https://is1-ssl.mzstatic.com/image/thumb/Music124/v4/af/c8/50/afc850e1-a11f-e789-af2f-14e11742255a/cover.jpg/100x100bb.jpg",
      "description": "Dieses Album ist ein Original-Hörspiel zur TV-Serie 'Robin Hood - Schlitzohr von Sherwood'. Es enthält 19 Teile eines Hörspiels.",
      "totalDuration": 0,
      "platforms": {
        "appleMusic": "1518807912"
      },
      "chapters": []
    },
    {
      "id": "1538565059",
      "title": "Folge 17: Flötenzauberei (Das Original Hörspiel zur TV-Serie)",
      "episodeNumber": null,
      "releaseDate": null,
      "coverURL": "https://is1-ssl.mzstatic.com/image/thumb/Music124/v4/6e/8e/e5/6e8ee58f-e900-4d1d-3c72-409d2257f753/cover.jpg/100x100bb.jpg",
      "description": "Dieses Album ist das Original-Hörspiel zur TV-Serie 'Robin Hood - Schlitzohr von Sherwood'. Es umfasst insgesamt 16 Tracks im Genre Hörspiele.",
      "totalDuration": 0,
      "platforms": {
        "appleMusic": "1538565059"
      },
      "chapters": []
    },
    {
      "id": "1558884959",
      "title": "Folge 18: Isabelle wird entführt (Das Original Hörspiel zur TV-Serie)",
      "episodeNumber": null,
      "releaseDate": null,
      "coverURL": "https://is1-ssl.mzstatic.com/image/thumb/Music114/v4/eb/9f/cb/eb9fcbe7-2654-7599-c6d3-adbd7fff9d7d/cover.jpg/100x100bb.jpg",
      "description": "Das Album beinhaltet ein Hörspiel basierend auf einer TV-Serie, das sich um den Abenteuerplot 'Isabelle wird entführt' dreht.",
      "totalDuration": 0,
      "platforms": {
        "appleMusic": "1558884959"
      },
      "chapters": []
    },
    {
      "id": "1572304948",
      "title": "Folge 19: Der verhexte Pokal (Das Original Hörspiel zur TV- Serie)",
      "episodeNumber": null,
      "releaseDate": null,
      "coverURL": "https://is1-ssl.mzstatic.com/image/thumb/Music125/v4/19/9c/ea/199cea9a-2e7b-3d6b-2033-685bdc118e16/cover.jpg/100x100bb.jpg",
      "description": "Dieses Album enthält das Originalhörspiel zur TV-Serie 'Robin Hood - Schlitzohr von Sherwood'. Es ist Teil einer Hörspielreihe, die dem Hörer ein spannendes Abenteuer bietet.",
      "totalDuration": 0,
      "platforms": {
        "appleMusic": "1572304948"
      },
      "chapters": []
    },
    {
      "id": "1299741323",
      "title": "Folge 1: Die Schatzkiste (Das Original-Hörspiel zur TV-Serie)",
      "episodeNumber": null,
      "releaseDate": null,
      "coverURL": "https://is1-ssl.mzstatic.com/image/thumb/Music125/v4/da/ca/21/daca21c1-85b8-2472-8d7b-cbf76d2c86e9/cover.jpg/100x100bb.jpg",
      "description": "Ein deutscher Hörspiel-Album, das das Original-Hörspiel zur TV-Serie 'Robin Hood - Schlitzohr von Sherwood' ist, mit insgesamt 31 Tracks im Genre Hörspiele.",
      "totalDuration": 0,
      "platforms": {
        "appleMusic": "1299741323"
      },
      "chapters": []
    },
    {
      "id": "1582965680",
      "title": "Folge 20: Schule für Gentlemen (Das Original-Hörspiel zur TV-Serie)",
      "episodeNumber": null,
      "releaseDate": null,
      "coverURL": "https://is1-ssl.mzstatic.com/image/thumb/Music115/v4/a6/c7/8f/a6c78f0b-6d03-29c7-57e3-4e65bdc48436/cover.jpg/100x100bb.jpg",
      "description": "Dieses Album ist das Original-Hörspiel zur TV-Serie 'Folge 20: Schule für Gentlemen' von Robin Hood - Schlitzohr von Sherwood.",
      "totalDuration": 0,
      "platforms": {
        "appleMusic": "1582965680"
      },
      "chapters": []
    },
    {
      "id": "1597936569",
      "title": "Folge 21: Ein königliches Geschenk (Das Original-Hörspiel zur TV-Serie)",
      "episodeNumber": null,
      "releaseDate": null,
      "coverURL": "https://is1-ssl.mzstatic.com/image/thumb/Music126/v4/37/ad/3e/37ad3e77-ee81-a104-9778-f260409731ad/cover.jpg/100x100bb.jpg",
      "description": "Dieses Album ist das Original-Hörspiel zur TV-Serie Robin Hood - Schlitzohr von Sherwood, das sich auf Abenteuer und Fantasy konzentriert.",
      "totalDuration": 0,
      "platforms": {
        "appleMusic": "1597936569"
      },
      "chapters": []
    },
    {
      "id": "1613912483",
      "title": "Folge 22: Scarlett und der Diamant (Das Original-Hörspiel zur TV-Serie)",
      "episodeNumber": null,
      "releaseDate": null,
      "coverURL": "https://is1-ssl.mzstatic.com/image/thumb/Music116/v4/4c/06/c5/4c06c5a5-0bf9-8429-b78a-3a82b6a3cc51/cover.jpg/100x100bb.jpg",
      "description": "Dieses Album enthält das Hörspiel 'Folge 22: Scarlett und der Diamant', das als Original-Hörspiel zur TV-Serie dient. Es ist klar als Hörspiel formatiert.",
      "totalDuration": 0,
      "platforms": {
        "appleMusic": "1613912483"
      },
      "chapters": []
    },
    {
      "id": "1628644709",
      "title": "Folge 23: Ein fieser Trick (Das Original-Hörspiel zur TV-Serie)",
      "episodeNumber": null,
      "releaseDate": null,
      "coverURL": "https://is1-ssl.mzstatic.com/image/thumb/Music122/v4/96/92/81/96928179-82c2-7773-49c1-11adaf2940f8/cover.jpg/100x100bb.jpg",
      "description": "Ein Hörspielalbum mit 19 Folgen, das das Original-Hörspiel zur TV-Serie 'Robin Hood - Schlitzohr von Sherwood' ist.",
      "totalDuration": 0,
      "platforms": {
        "appleMusic": "1628644709"
      },
      "chapters": []
    },
    {
      "id": "1636040237",
      "title": "Folge 24: Der Drachenstein (Das Original-Hörspiel zur TV-Serie)",
      "episodeNumber": null,
      "releaseDate": null,
      "coverURL": "https://is1-ssl.mzstatic.com/image/thumb/Music122/v4/aa/3e/d5/aa3ed531-7973-36a3-dcd6-cf8bd61d31ef/cover.jpg/100x100bb.jpg",
      "description": "Dieses Album enthält ein Original-Hörspiel zur TV-Serie 'Robin Hood - Schlitzohr von Sherwood' mit 16 Folgen, das sich auf Abenteuer und Fantasy konzentriert.",
      "totalDuration": 0,
      "platforms": {
        "appleMusic": "1636040237"
      },
      "chapters": []
    },
    {
      "id": "1644370437",
      "title": "Folge 25: Der König und das Huhn (Das Original-Hörspiel zur TV-Serie)",
      "episodeNumber": null,
      "releaseDate": null,
      "coverURL": "https://is1-ssl.mzstatic.com/image/thumb/Music122/v4/bc/39/5e/bc395edf-e599-a630-b631-880e988d1491/cover.jpg/100x100bb.jpg",
      "description": "Dieses Album enthält das Original-Hörspiel zur TV-Serie 'Robin Hood - Schlitzohr von Sherwood' mit 17 Folgen. Es ist ein Hörspielalbum, das auf iTunes verfügbar ist.",
      "totalDuration": 0,
      "platforms": {
        "appleMusic": "1644370437"
      },
      "chapters": []
    },
    {
      "id": "1651860631",
      "title": "Folge 26: Der wahre König (Das Original-Hörspiel zur TV-Serie)",
      "episodeNumber": null,
      "releaseDate": null,
      "coverURL": "https://is1-ssl.mzstatic.com/image/thumb/Music122/v4/76/75/17/7675179c-2e9d-b3b8-2f36-0b955ae9c237/cover.jpg/100x100bb.jpg",
      "description": "Das Album enthält das Original-Hörspiel zur TV-Serie 'Robin Hood - Schlitzohr von Sherwood'.",
      "totalDuration": 0,
      "platforms": {
        "appleMusic": "1651860631"
      },
      "chapters": []
    },
    {
      "id": "1777035898",
      "title": "Folge 27: Die Bedrohung (Das Original-Hörspiel zur TV-Serie)",
      "episodeNumber": null,
      "releaseDate": null,
      "coverURL": "https://is1-ssl.mzstatic.com/image/thumb/Music211/v4/be/d6/7d/bed67d73-ecba-144c-5e0f-c71fa0ddf524/cover.jpg/100x100bb.jpg",
      "description": "Dieses Album ist das Original-Hörspiel zur TV-Serie 'Robin Hood - Schlitzohr von Sherwood'. Es enthält insgesamt 25 Tracks im Genre Hörspiel.",
      "totalDuration": 0,
      "platforms": {
        "appleMusic": "1777035898"
      },
      "chapters": []
    },
    {
      "id": "1803976762",
      "title": "Folge 28: Prinzessin in Gefahr (Das Original-Hörspiel zur TV-Serie)",
      "episodeNumber": null,
      "releaseDate": null,
      "coverURL": "https://is1-ssl.mzstatic.com/image/thumb/Music221/v4/f4/da/a1/f4daa1ee-a6cc-83d0-dc4f-c12851eb5935/cover.jpg/100x100bb.jpg",
      "description": "Dieses Album enthält das Original-Hörspiel zur TV-Serie 'Robin Hood - Schlitzohr von Sherwood', das sich auf die Handlung und Abenteuer der Figur konzentriert.",
      "totalDuration": 0,
      "platforms": {
        "appleMusic": "1803976762"
      },
      "chapters": []
    },
    {
      "id": "1778487060",
      "title": "Folge 29: Das Überraschungsbrot (Das Original-Hörspiel zur TV-Serie)",
      "episodeNumber": null,
      "releaseDate": null,
      "coverURL": "https://is1-ssl.mzstatic.com/image/thumb/Music221/v4/62/ea/5b/62ea5b82-be8f-2303-ee06-b7684fdb5927/cover.jpg/100x100bb.jpg",
      "description": "Ein Original-Hörspiel zur TV-Serie, das auf 23 Tracks verteilt ist.",
      "totalDuration": 0,
      "platforms": {
        "appleMusic": "1778487060"
      },
      "chapters": []
    },
    {
      "id": "1298051501",
      "title": "Folge 2: Der König der Diebe (Das Original-Hörspiel zur TV-Serie)",
      "episodeNumber": null,
      "releaseDate": null,
      "coverURL": "https://is1-ssl.mzstatic.com/image/thumb/Music125/v4/b7/10/23/b71023d0-819c-039a-ee49-e7caabcdc20b/cover.jpg/100x100bb.jpg",
      "description": "Ein Hörspielalbum basierend auf der TV-Serie 'Robin Hood - Schlitzohr von Sherwood', das Abenteuer und Spannung bietet.",
      "totalDuration": 0,
      "platforms": {
        "appleMusic": "1298051501"
      },
      "chapters": []
    },
    {
      "id": "1778487898",
      "title": "Folge 30: Das teuflische Trio (Das Original-Hörspiel zur TV-Serie)",
      "episodeNumber": null,
      "releaseDate": null,
      "coverURL": "https://is1-ssl.mzstatic.com/image/thumb/Music221/v4/71/8a/8b/718a8b1b-9007-d172-b8ed-c6451ca3a76a/cover.jpg/100x100bb.jpg",
      "description": "Dieses Album ist das Original-Hörspiel zur TV-Serie 'Robin Hood - Schlitzohr von Sherwood' mit 24 Folgen. Es passt perfekt zu den Genres Hörspiel und Krimi.",
      "totalDuration": 0,
      "platforms": {
        "appleMusic": "1778487898"
      },
      "chapters": []
    },
    {
      "id": "1778478318",
      "title": "Folge 31: Der Blaubeeraufstand (Das Original-Hörspiel zur TV-Serie)",
      "episodeNumber": null,
      "releaseDate": null,
      "coverURL": "https://is1-ssl.mzstatic.com/image/thumb/Music211/v4/63/22/46/63224686-40b2-7a58-1c98-891dddc31034/cover.jpg/100x100bb.jpg",
      "description": "Dieses Album enthält das Original-Hörspiel zur TV-Serie 'Robin Hood - Schlitzohr von Sherwood' mit insgesamt 24 Folgen.",
      "totalDuration": 0,
      "platforms": {
        "appleMusic": "1778478318"
      },
      "chapters": []
    },
    {
      "id": "1778478217",
      "title": "Folge 32: Odins Prüfung (Das Original-Hörspiel zur TV-Serie)",
      "episodeNumber": null,
      "releaseDate": null,
      "coverURL": "https://is1-ssl.mzstatic.com/image/thumb/Music221/v4/63/73/ae/6373ae6b-2aa9-13f5-ff1f-578a32d8d081/cover.jpg/100x100bb.jpg",
      "description": "Ein Hörspiel zur TV-Serie, das auf einer mythologischen Geschichte basiert.",
      "totalDuration": 0,
      "platforms": {
        "appleMusic": "1778478217"
      },
      "chapters": []
    },
    {
      "id": "1804066071",
      "title": "Folge 33: Unter Schock (Das Original-Hörspiel zur TV-Serie)",
      "episodeNumber": null,
      "releaseDate": null,
      "coverURL": "https://is1-ssl.mzstatic.com/image/thumb/Music221/v4/8b/70/80/8b7080ee-c747-427c-f871-2a5c89396035/cover.jpg/100x100bb.jpg",
      "description": "Das Album enthält das Original-Hörspiel zur TV-Serie 'Robin Hood - Schlitzohr von Sherwood', das 18 Geschichten umfasst.",
      "totalDuration": 0,
      "platforms": {
        "appleMusic": "1804066071"
      },
      "chapters": []
    },
    {
      "id": "1804945500",
      "title": "Folge 34: Fauler Zauber (Das Original-Hörspiel zur TV-Serie)",
      "episodeNumber": null,
      "releaseDate": null,
      "coverURL": "https://is1-ssl.mzstatic.com/image/thumb/Music221/v4/e6/94/34/e6943455-9dfe-4aa4-fdc3-820944040358/cover.jpg/100x100bb.jpg",
      "description": "Dieses Album ist ein Original-Hörspiel zur TV-Serie 'Robin Hood - Schlitzohr von Sherwood'. Es umfasst 18 Tracks im Genre Hörspiele.",
      "totalDuration": 0,
      "platforms": {
        "appleMusic": "1804945500"
      },
      "chapters": []
    },
    {
      "id": "1804943740",
      "title": "Folge 35: Mit verbundenen Augen (Das Original-Hörspiel zur TV-Serie)",
      "episodeNumber": null,
      "releaseDate": null,
      "coverURL": "https://is1-ssl.mzstatic.com/image/thumb/Music221/v4/4f/0f/00/4f0f00b2-ccfd-9328-3239-242ae63516ad/cover.jpg/100x100bb.jpg",
      "description": "Dieses Album enthält das Original-Hörspiel zur TV-Serie 'Robin Hood - Schlitzohr von Sherwood'. Es ist Teil des Hörspielgenres.",
      "totalDuration": 0,
      "platforms": {
        "appleMusic": "1804943740"
      },
      "chapters": []
    },
    {
      "id": "1298052041",
      "title": "Folge 3: Das Pferderennen (Das Original-Hörspiel zur TV-Serie)",
      "episodeNumber": null,
      "releaseDate": null,
      "coverURL": "https://is1-ssl.mzstatic.com/image/thumb/Music125/v4/81/82/92/818292fa-c6ed-d3a2-0100-1c6cf51b91d2/cover.jpg/100x100bb.jpg",
      "description": "Dieses Album enthält ein Original-Hörspiel zur TV-Serie, das als Hörbuch formatiert verfügbar ist.",
      "totalDuration": 0,
      "platforms": {
        "appleMusic": "1298052041"
      },
      "chapters": []
    },
    {
      "id": "1300522513",
      "title": "Folge 4: Der magische Pfeil (Das Original-Hörspiel zur TV-Serie)",
      "episodeNumber": null,
      "releaseDate": null,
      "coverURL": "https://is1-ssl.mzstatic.com/image/thumb/Music115/v4/a2/77/f0/a277f05c-0c00-fa19-8c7e-ccff9acb9375/cover.jpg/100x100bb.jpg",
      "description": "Dieses Album enthält das Original-Hörspiel zur TV-Serie 'Robin Hood - Schlitzohr von Sherwood' und besteht aus 25 Hörspielen.",
      "totalDuration": 0,
      "platforms": {
        "appleMusic": "1300522513"
      },
      "chapters": []
    },
    {
      "id": "1567214042",
      "title": "Folge 5: Die neuen Sheriffs (Das Original-Hörspiel zur TV-Serie)",
      "episodeNumber": null,
      "releaseDate": null,
      "coverURL": "https://is1-ssl.mzstatic.com/image/thumb/Music115/v4/59/cf/9e/59cf9e03-5878-e422-2127-f2de894fd868/cover.jpg/100x100bb.jpg",
      "description": "Dieses Album ist ein Original-Hörspiel zur TV-Serie, das Teil eines deutschen Hörspiel-Angebots ist.",
      "totalDuration": 0,
      "platforms": {
        "appleMusic": "1567214042"
      },
      "chapters": []
    },
    {
      "id": "1567214544",
      "title": "Folge 6: Der Schlossgeist (Das Original-Hörspiel zur TV-Serie)",
      "episodeNumber": null,
      "releaseDate": null,
      "coverURL": "https://is1-ssl.mzstatic.com/image/thumb/Music115/v4/49/47/9e/49479e2e-8974-b9ee-826d-cfa7adef22a7/cover.jpg/100x100bb.jpg",
      "description": "Das Album enthält das Original-Hörspiel zur TV-Serie 'Robin Hood - Schlitzohr von Sherwood', das aus 18 Folgen besteht und sich auf das Genre des Hörspiels konzentriert.",
      "totalDuration": 0,
      "platforms": {
        "appleMusic": "1567214544"
      },
      "chapters": []
    },
    {
      "id": "1567213679",
      "title": "Folge 7: Prinzenparty (Das Original-Hörspiel zur TV-Serie)",
      "episodeNumber": null,
      "releaseDate": null,
      "coverURL": "https://is1-ssl.mzstatic.com/image/thumb/Music125/v4/10/6e/4b/106e4b64-2738-58c4-4513-214083f414d4/cover.jpg/100x100bb.jpg",
      "description": "Ein Hörspielalbum zur TV-Serie, das als Original-Hörspiel veröffentlicht wurde.",
      "totalDuration": 0,
      "platforms": {
        "appleMusic": "1567213679"
      },
      "chapters": []
    },
    {
      "id": "1567214654",
      "title": "Folge 8: Spiegel-Marian (Das Original-Hörspiel zur TV-Serie)",
      "episodeNumber": null,
      "releaseDate": null,
      "coverURL": "https://is1-ssl.mzstatic.com/image/thumb/Music115/v4/42/88/c9/4288c90c-5b28-cfb5-ed5b-1f2626c135b9/cover.jpg/100x100bb.jpg",
      "description": "Dieses Album ist das Original-Hörspiel zur TV-Serie 'Robin Hood - Schlitzohr von Sherwood'. Es umfasst 17 Tracks im Genre Hörspiel.",
      "totalDuration": 0,
      "platforms": {
        "appleMusic": "1567214654"
      },
      "chapters": []
    },
    {
      "id": "1199905224",
      "title": "Folge 9: Geld für die Waisenkinder (Das Original-Hörspiel zur TV-Serie)",
      "episodeNumber": null,
      "releaseDate": null,
      "coverURL": "https://is1-ssl.mzstatic.com/image/thumb/Music125/v4/1b/92/89/1b92890f-86fa-295f-77e0-d70e10911361/cover.jpg/100x100bb.jpg",
      "description": "Das Album enthält das Original-Hörspiel zur TV-Serie 'Robin Hood - Schlitzohr von Sherwood' mit 16 Folgen über Geld für Waisenkinder.",
      "totalDuration": 0,
      "platforms": {
        "appleMusic": "1199905224"
      },
      "chapters": []
    }
  ],
  "updatedAt": "2026-05-27T17:19:36Z"
}